{
    "ManagementPackSystemName":  "Windows.Server.Webservice.LogdirectoryWatcher",
    "ManagementPackDisplayName":  "Windows Server Webservice LogdirectoryWatcher",
    "URL":  "https://github.com/Juanito99/Windows.Server.Webservice.LogdirectoryWatcher",
    "Version":  "1.0.0.353",
    "Author":  "Ruben Zimmermann",
    "Description":  "Management Pack which monitors the webserver\u0027s log directory size. Covers IIS, Apache and ApacheTomcat on Windows Server. It offers recovery tasks for automatic log rotation",
    "IsFree":  true,
    "Tags":  [
                 "IIS",
                 "Apache",
                 "ApacheTomcat",
                 "Log directory"
             ]
}
